castepkit/__init__.py
castepkit/_version.py
castepkit/config.py
castepkit/switch.py
castepkit/utils.py
castepkit/dummy_bin/atom_cutting.py
castepkit/dummy_bin/ome.py
castepkit/dummy_bin/shg.py
castepkit/dummy_bin/weighted_den.py
castepkit/scripts/__init__.py
castepkit/scripts/create_switch.py
castepkit/wrappers/__init__.py
castepkit/wrappers/atom_cutting.py
castepkit/wrappers/ome.py
castepkit/wrappers/shg.py
castepkit/wrappers/weighted_dens.py
castepkit-0.0.10.dist-info/licenses/LICENSE
castepkit-0.0.10.dist-info/METADATA
castepkit-0.0.10.dist-info/WHEEL
castepkit-0.0.10.dist-info/entry_points.txt
castepkit-0.0.10.dist-info/top_level.txt
castepkit-0.0.10.dist-info/RECORD
