Metadata-Version: 2.4
Name: castepkit
Version: 0.0.10
Summary: Tools for processing outputs from CASTEP program.
Author-email: YingXing Cheng <yxcheng2buaa@gmail.com>
Maintainer-email: YingXing Cheng <yxcheng2buaa@gamil.com>
License:                    GNU LESSER GENERAL PUBLIC LICENSE
Project-URL: Homepage, https://github.com/yingxingcheng/castepkit
Project-URL: Repository, https://github.com/yingxingcheng/castepkit
Project-URL: Changelog, https://github.com/yingxingcheng/castepkit/CHANGELOG.md
Keywords: Abinit calculations,Computational chemistry
Classifier: Development Status :: 3 - Alpha
Classifier: Environment :: Console
Classifier: Intended Audience :: Science/Research
Classifier: Intended Audience :: Education
Classifier: Framework :: Matplotlib
Classifier: License :: OSI Approved :: GNU General Public License v3 or later (GPLv3+)
Classifier: Natural Language :: English
Classifier: Operating System :: POSIX
Classifier: Operating System :: MacOS
Classifier: Programming Language :: Python :: 3
Classifier: Topic :: Scientific/Engineering
Requires-Python: >=3.9
License-File: LICENSE
Requires-Dist: toml
Requires-Dist: platformdirs
Requires-Dist: castep_outputs
Provides-Extra: dev
Requires-Dist: pre-commit; extra == "dev"
Provides-Extra: tests
Requires-Dist: pytest; extra == "tests"
Requires-Dist: pytest-skip-slow; extra == "tests"
Dynamic: license-file
